nfctagger/__init__.py
nfctagger/__main__.py
nfctagger/data.py
nfctagger/ndef.py
nfctagger/py.typed
nfctagger/tlv.py
nfctagger/devices/__init__.py
nfctagger/devices/acr122.py
nfctagger/devices/ntag.py
nfctagger/devices/pcsc.py
nfctagger/devices/pn53x.py
nfctagger-0.0.2.dist-info/METADATA
nfctagger-0.0.2.dist-info/WHEEL
nfctagger-0.0.2.dist-info/licenses/LICENSE
nfctagger-0.0.2.dist-info/RECORD
