Metadata-Version: 2.4
Name: nfctagger
Version: 0.0.2
Summary: Add your description here
Project-URL: Homepage, https://github.com/pbutler/nfctagger
Project-URL: Issues, https://github.com/pbutler/nfctagger/issues
Author-email: Patrick Butler <pbutler@killertux.org>
License-Expression: MIT
License-File: LICENSE
Classifier: Development Status :: 3 - Alpha
Classifier: Operating System :: OS Independent
Classifier: Programming Language :: Python :: 3
Requires-Python: >=3.9
Requires-Dist: construct>=2.10.70
Requires-Dist: loguru>=0.7.3
Requires-Dist: ndeflib>=0.3.3
Requires-Dist: pyscard>=2.2.1
